{
    "version": "7",
    "dialect": "sqlite",
    "entries": [
        {
            "idx": 0,
            "version": "6",
            "when": 1768743538889,
            "tag": "0000_initial",
            "breakpoints": true
        },
        {
            "idx": 1,
            "version": "6",
            "when": 1770044285634,
            "tag": "0001_archivization",
            "breakpoints": true
        },
        {
            "idx": 2,
            "version": "6",
            "when": 1770056487825,
            "tag": "0002_attachments",
            "breakpoints": true
        },
        {
            "idx": 3,
            "version": "6",
            "when": 1770060504950,
            "tag": "0003_uuids",
            "breakpoints": true
        },
        {
            "idx": 4,
            "version": "6",
            "when": 1770063750501,
            "tag": "0004_invitation_tokens",
            "breakpoints": true
        },
        {
            "idx": 5,
            "version": "6",
            "when": 1770113879478,
            "tag": "0005_exchange_rates",
            "breakpoints": true
        },
        {
            "idx": 6,
            "version": "6",
            "when": 1770664564972,
            "tag": "0006_activities",
            "breakpoints": true
        }
    ]
}
